{
  "adapter_ids": {
    "canonical_timing": "canonical_cutoff_coverage_normalized_v1",
    "support_repaired": "support_constrained_coverage_normalized_v1"
  },
  "common_activation_utc": "2026-07-19T15:00:00+00:00",
  "coverage": {
    "canonical_minus_support_rows": 138,
    "canonical_share_of_original": 0.6528925619834711,
    "support_share_of_original": 0.08264462809917356
  },
  "inputs": {
    "canonical_timing": {
      "path": "prospective-data/data/derived/latest/canonical-timing-shadow/canonical-timing-event-candidates.csv.gz",
      "rows": 158,
      "sha256": "57a7ec1c612cf741ec5c3a3ad036a8ae260e19d76a9537866fd582ac6b1480a0"
    },
    "original": {
      "path": "prospective-data/data/derived/latest/shadow/event-shadow-candidates.csv.gz",
      "rows": 288,
      "sha256": "1c5d7e8f5d273ae3d2440922b169d7a7a373258a2444c2b1567bbe92a384042a"
    },
    "support_repaired": {
      "path": "prospective-data/data/derived/latest/support-repaired-shadow/support-repaired-event-candidates.csv.gz",
      "rows": 20,
      "sha256": "d968d41d5bd7e1b9692f3ef9b5d5bf7b2a29d547f3e6c2d2c818ea397901cc0e"
    }
  },
  "outcome_blind": true,
  "pairs": {
    "original_vs_canonical": {
      "action_spearman": 0.8137626786035829,
      "intersection": 158,
      "jaccard": 0.6528925619834711,
      "left_only": 84,
      "raw_spearman": 0.7993382596230391,
      "right_only": 0,
      "same_bookmaker_share": 0.8354430379746836,
      "same_outcome_share": 0.8924050632911392,
      "union": 242
    },
    "original_vs_support": {
      "action_spearman": 0.8962406015037594,
      "intersection": 20,
      "jaccard": 0.08264462809917356,
      "left_only": 222,
      "raw_spearman": 0.9518796992481202,
      "right_only": 0,
      "same_bookmaker_share": 0.8,
      "same_outcome_share": 0.9,
      "union": 242
    },
    "support_vs_canonical": {
      "action_spearman": 1.0,
      "intersection": 20,
      "jaccard": 0.12658227848101267,
      "left_only": 0,
      "raw_spearman": 1.0,
      "right_only": 138,
      "same_bookmaker_share": 1.0,
      "same_outcome_share": 1.0,
      "union": 158
    }
  },
  "streams": {
    "canonical_timing": {
      "events": 44,
      "rows": 158,
      "rows_by_cutoff": {
        "12": 15,
        "24": 103,
        "48": 36,
        "6": 4
      },
      "snapshots": 37
    },
    "original": {
      "events": 53,
      "rows": 242,
      "rows_by_cutoff": {
        "12": 15,
        "24": 103,
        "48": 117,
        "6": 7
      },
      "snapshots": 40
    },
    "support_repaired": {
      "events": 14,
      "rows": 20,
      "rows_by_cutoff": {
        "12": 5,
        "24": 5,
        "48": 6,
        "6": 4
      },
      "snapshots": 9
    }
  }
}